pyserilog_formating_elasticsearch/__init__.py
pyserilog_formating_elasticsearch/default_json_formatter.py
pyserilog_formating_elasticsearch/elasticsearch_json_formatter.py
pyserilog_formating_elasticsearch/conf/__init__.py
pyserilog_formating_elasticsearch/conf/config.py
pyserilog_formating_elasticsearch/conf/constants.py
pyserilog_formating_elasticsearch/utils/__init__.py
pyserilog_formating_elasticsearch/utils/encoding.py
pyserilog_formating_elasticsearch/utils/processors.py
pyserilog_formating_elasticsearch/utils/stacks.py
pyserilog_sinks_elasticsearch/__init__.py
pyserilog_sinks_elasticsearch/elasticsearch_sink.py
pyserilog_sinks_elasticsearch/elasticsearch_sink_state.py
pyserilog_sinks_elasticsearch/elasticsearch_version_manager.py
pyserilog_sinks_elasticsearch/enums.py
pyserilog_sinks_elasticsearch/extensions.py
pyserilog_sinks_elasticsearch/options.py
pyserilog_sinks_elasticsearch/provider.py
pyserilog_sinks_elasticsearch/sinks/__init__.py
pyserilog_sinks_elasticsearch/sinks/elasticsearch_sink.py
pyserilog_sinks_elasticsearch/sinks/elasticsearch_sink_state.py
pyserilog_sinks_elasticsearch/sinks/elasticsearch_version_manager.py
pyserilog_sinks_elasticsearch/sinks/enums.py
pyserilog_sinks_elasticsearch/sinks/options.py
pyserilog_sinks_elasticsearch/sinks/provider.py
pyserilog_sinks_elasticsearch-0.2.0.dist-info/LICENSE
pyserilog_sinks_elasticsearch-0.2.0.dist-info/METADATA
pyserilog_sinks_elasticsearch-0.2.0.dist-info/WHEEL
pyserilog_sinks_elasticsearch-0.2.0.dist-info/top_level.txt
pyserilog_sinks_elasticsearch-0.2.0.dist-info/RECORD
